go_optouts/__init__.py
go_optouts/api.py
go_optouts/auth.py
go_optouts/main.py
go_optouts/server.py
go_optouts/backends/__init__.py
go_optouts/backends/tests/__init__.py
go_optouts/store/__init__.py
go_optouts/store/interface.py
go_optouts/store/memory.py
go_optouts/store/riak.py
go_optouts/store/tests/__init__.py
go_optouts/store/tests/test_memory.py
go_optouts/store/tests/test_riak.py
go_optouts/tests/__init__.py
go_optouts/tests/test_api.py
go_optouts/tests/test_auth.py
go_optouts/tests/test_main.py
go_optouts/tests/test_server.py
go_optouts/tests/utils.py
go_optouts-0.1.2.dist-info/DESCRIPTION.rst
go_optouts-0.1.2.dist-info/METADATA
go_optouts-0.1.2.dist-info/RECORD
go_optouts-0.1.2.dist-info/WHEEL
go_optouts-0.1.2.dist-info/entry_points.txt
go_optouts-0.1.2.dist-info/metadata.json
go_optouts-0.1.2.dist-info/top_level.txt
