Metadata-Version: 2.0
Name: go-optouts
Version: 0.1.2
Summary: An API for managing Vumi Go opt outs.
Home-page: http://github.com/praekelt/go-optouts-api
Author: Praekelt Foundation
Author-email: dev@praekeltfoundation.org
License: BSD
Platform: UNKNOWN
Classifier: Development Status :: 4 - Beta
Classifier: Intended Audience :: Developers
Classifier: License :: OSI Approved :: BSD License
Classifier: Operating System :: POSIX
Classifier: Programming Language :: Python
Classifier: Topic :: Software Development :: Libraries :: Python Modules
Classifier: Topic :: Internet :: WWW/HTTP
Requires-Dist: PyYAML
Requires-Dist: Twisted (>=13.1.0)
Requires-Dist: click
Requires-Dist: klein
Requires-Dist: treq
Requires-Dist: vumi (>=0.5.4)
Requires-Dist: vumi-go
